HomeTask_2/sr_and_latch.v
module sr_and_latch (
	r_i, // reset
	s_i, // set 
	q_o,
	qn_o
);

input  wire		r_i;
input  wire 	s_i;
output wire		q_o;
output wire		qn_o;

assign q_o = ~ (s_i & qn_o);
assign qn_o = ~ (r_i & q_o);

endmodule

HomeTask_2/d_latch.v
module d_latch (
    d_i, // data
    c_i, // condition
    q_o,
    qn_o
);

input	wire		d_i;
input 	wire		c_i;
output  wire		q_o;
output  wire		qn_o;

wire r;
wire s;

assign r = ~(c_i & (~d_i));
assign s = ~(d_i & c_i);

sr_and_latch sr_latch_inst(
	.r_i(r),          // after dot name of variable from original module, in brackets name of local variable
	.s_i(s), 
	.q_o(q_o),
	.qn_o(qn_o)
	);

endmodule

HomeTask_2/d_flip_flop.v
module d_flip_flop(
    d_i; // data
    c_i; // condition
    q_o;
    qn_o;
);

input   wire    d_i;
input   wire    c_i;
output  wire    q_o;
output  wire    qn_o;

wire qm;

d_latch d_latch_master(
    .d_i(d_i); 
    .c_i(~c_i); 
    .q_o(qm);
  );

d_latch d_latch_slave(
    .d_i(qm); 
    .c_i(c_i); 
    .q_o(q_o);
    .qn_o(qn_o);
  );

endmodule

HomeTask_2/d_flip_flop_tb.v
`timescale 1ns/10ps

module d_flip_flop_tb();

reg DATA; // registers for input signals
reg COND; 
wire Q;   // wires for output signals
wire QN; 

integer i; // loop
realtime period = 10; // setting period variable
reg [3:0] delay;
integer seed = 4; // urandom

d_flip_flop d_flip_flop_inst(
    .d_i(DATA), // data
    .c_i(COND), // condition
    .q_o(Q),
    .qn_o(QN)
);


always #(period) COND = ~COND; // setting clk inverting every period 

initial 
begin
    $dumpvars;
    COND = 1'b0;
    DATA = 1'b0;

    for (i = 0; i < 50; i = i + 1)
    begin
        delay = $urandom(seed) % 10 + 1;
        #(delay) DATA = ~DATA; 
    end

    #100 $finish;
end

initial
begin
    $monitor("simtime = %g, DATA =%b, COND =%b, Q =%b, QN =%b", $time,DATA,COND,Q, QN);
end

endmodule

HomeTask_2/dump.vcd
$date
	Sat Apr  2 03:32:32 2022
$end
$version
	Icarus Verilog
$end
$timescale
	10ps
$end
$scope module d_flip_flop_tb $end
$var wire 1 ! QN $end
$var wire 1 " Q $end
$var reg 1 # COND $end
$var reg 1 $ DATA $end
$var reg 4 % delay [3:0] $end
$var integer 32 & i [31:0] $end
$var real 1 ' period $end
$var integer 32 ( seed [31:0] $end
$scope module d_flip_flop_inst $end
$var wire 1 # c_i $end
$var wire 1 $ d_i $end
$var wire 1 ! qn_o $end
$var wire 1 ) qm $end
$var wire 1 " q_o $end
$scope module d_latch_master $end
$var wire 1 * c_i $end
$var wire 1 $ d_i $end
$var wire 1 + r $end
$var wire 1 , s $end
$var wire 1 - qn_o $end
$var wire 1 ) q_o $end
$scope module sr_latch_inst $end
$var wire 1 ) q_o $end
$var wire 1 - qn_o $end
$var wire 1 + r_i $end
$var wire 1 , s_i $end
$upscope $end
$upscope $end
$scope module d_latch_slave $end
$var wire 1 # c_i $end
$var wire 1 ) d_i $end
$var wire 1 . r $end
$var wire 1 / s $end
$var wire 1 ! qn_o $end
$var wire 1 " q_o $end
$scope module sr_latch_inst $end
$var wire 1 " q_o $end
$var wire 1 ! qn_o $end
$var wire 1 . r_i $end
$var wire 1 / s_i $end
$upscope $end
$upscope $end
$upscope $end
$upscope $end
$enddefinitions $end
#0
$dumpvars
1/
1.
1-
1,
0+
1*
0)
b1000011011100110101 (
r10 '
b0 &
b1 %
0$
0#
x"
x!
$end
#100
0-
1)
1+
0,
b101 %
b1110001011000101110011001110010 (
b1 &
1$
#600
0)
1-
0+
1,
b10111000010110000101001101001011 (
b10 &
0$
#1000
0"
1!
1+
0.
0*
1#
#1100
b111 %
b1101110010000001000001000010000 (
b11 &
1$
#1800
b101 %
b10010010100101111011011010001 (
b100 &
0$
#2000
0+
1.
1*
0#
#2300
0-
1)
1+
0,
b10 %
b11011001110010010100001001011110 (
b101 &
1$
#2500
0)
1-
0+
1,
b1010 %
b11100000111001101110101101000111 (
b110 &
0$
#3000
1+
0.
0*
1#
#3500
b1 %
b10111110001001000000001011011100 (
b111 &
1$
#3600
b10 %
b11001110101110111011000101101 (
b1000 &
0$
#3800
b11000101101101110101100001010 (
b1001 &
1$
#4000
0+
1.
1*
b111 %
b11111111011100111011100100000011 (
b1010 &
0$
0#
#4700
0-
1)
1+
0,
b11 %
b101001000100110100111001101000 (
b1011 &
1$
#5000
0!
1"
1,
0/
0*
b10 %
b101101110110010001000101001001 (
b1100 &
0$
1#
#5200
b110 %
b11001101111111001000110001110110 (
b1101 &
1$
#5800
b10 %
b1010010110101000111100001111111 (
b1110 &
0$
#6000
0,
1/
1*
b10010110110000011111000010110100 (
b1111 &
1$
0#
#6200
0)
1-
0+
1,
b111 %
b10000011001110101110010000100101 (
b10000 &
0$
#6900
0-
1)
1+
0,
b1000 %
b11110111111000111001001010100010 (
b10001 &
1$
#7000
1,
0/
0*
1#
#7700
b11 %
b10100010010100001010010110111011 (
b10010 &
0$
#8000
0,
1/
1*
b100 %
b10111000101110100011010111000000 (
b10011 &
1$
0#
#8400
0)
1-
0+
1,
b1010 %
b10010111100101111100101011000001 (
b10100 &
0$
#9000
0"
1!
1+
0.
0*
1#
#9400
b10 %
b11100100100110100010100110001110 (
b10101 &
1$
#9600
b101 %
b1101000111010111110010110111 (
b10110 &
0$
#10000
0+
1.
1*
0#
#10100
0-
1)
1+
0,
b1010 %
b1111100101010010010100110001100 (
b10111 &
1$
#11000
0!
1"
1,
0/
0*
1#
#11100
b11 %
b10010100000111100110000100011101 (
b11000 &
0$
#11400
b1 %
b10001000010111110011110100111010 (
b11001 &
1$
#11500
b1000 %
b1000111100110011111100101110011 (
b11010 &
0$
#12000
0)
1-
0+
1/
1*
0#
#12300
0-
1)
1+
0,
b101 %
b100001011010101001100000011000 (
b11011 &
1$
#12800
0)
1-
0+
1,
b11 %
b11000100001011010000001100111001 (
b11100 &
0$
#13000
0"
1!
1+
0.
0*
1#
#13100
b1100100011011100111100110100110 (
b11101 &
1$
#13400
b1 %
b10000010010010101101011111101111 (
b11110 &
0$
#13500
b100 %
b11111010110101010000110101100100 (
b11111 &
1$
#13900
b10 %
b10111011101011011100110100010101 (
b100000 &
0$
#14000
0+
1.
1*
0#
#14100
0-
1)
1+
0,
b11101010101011000100101011010010 (
b100001 &
1$
#14300
0)
1-
0+
1,
b1010 %
b11110110100101101001010000101011 (
b100010 &
0$
#15000
1+
0.
0*
1#
#15300
b111 %
b10110000010001011101010101110000 (
b100011 &
1$
#16000
0+
1.
1*
b11 %
b10001001001100101001101010110001 (
b100100 &
0$
0#
#16300
0-
1)
1+
0,
b101 %
b1010000100011101110010111110 (
b100101 &
1$
#16800
0)
1-
0+
1,
b11 %
b11010101010000010110101000100111 (
b100110 &
0$
#17000
1+
0.
0*
1#
#17100
b100 %
b10000001111011001111110000111100 (
b100111 &
1$
#17500
b110 %
b1111110100010000100000001101 (
b101000 &
0$
#18000
0+
1.
1*
0#
#18100
0-
1)
1+
0,
b100 %
b1001111110110010001101101101010 (
b101001 &
1$
#18500
0)
1-
0+
1,
b110 %
b10010101010010101010111100011 (
b101010 &
0$
#19000
1+
0.
0*
1#
#19100
b100 %
b11100000110110010100110111001000 (
b101011 &
1$
#19500
b110 %
b1100100101111100111000100101001 (
b101100 &
0$
#20000
0+
1.
1*
0#
#20100
0-
1)
1+
0,
b11 %
b11001001011010001011001011010110 (
b101101 &
1$
#20400
0)
1-
0+
1,
b100 %
b1001100110000100001001101011111 (
b101110 &
0$
#20800
0-
1)
1+
0,
b1100101110001000101011000010100 (
b101111 &
1$
#21000
0!
1"
1,
0/
0*
1#
#21200
b11001100101010111111001000000101 (
b110000 &
0$
#21600
b11 %
b10010011000000000000111100000010 (
b110001 &
1$
#21900
b110010 &
0$
#22000
0)
1-
0+
1/
1*
0#
#23000
0"
1!
1+
0.
0*
1#
#24000
0+
1.
1*
0#
#25000
1+
0.
0*
1#
#26000
0+
1.
1*
0#
#27000
1+
0.
0*
1#
#28000
0+
1.
1*
0#
#29000
1+
0.
0*
1#
#30000
0+
1.
1*
0#
#31000
1+
0.
0*
1#
