HomeTask_2/sr_latch.v
module sr_latch (
	r_i, // reset
	s_i, // set 
	q_o,
	qn_o
);

input  wire		r_i;
input  wire 	s_i;
output wire		q_o;
output wire		qn_o;

assign q_o = ~ (r_i | qn_o);
assign qn_o = ~ (s_i | q_o);

endmodule

HomeTask_2/d_latch.v
module d_latch (
    d_i, // data
    c_i, // condition
    q_o,
    qn_o
);

input	wire		d_i;
input 	wire		c_i;
output  wire		q_o;
output  wire		qn_o;

wire r;
wire s;

assign r = ~(c_i & (~d_i));
assign s = ~(d_i & c_i);

sr_latch sr_latch_inst(
	.r_i(r),          // after dot name of variable from original module, in brackets name of local variable
	.s_i(s), 
	.q_o(q_o),
	.qn_o(qn_o)
	);

endmodule

HomeTask_2/d_flip_flop.v
module d_flip_flop(
    d_i, // data
    c_i, // condition
    q_o,
    qn_o
);

input   wire    d_i;
input   wire    c_i;
output  wire    q_o;
output  wire    qn_o;

wire qm;

d_latch d_latch_master(
    .d_i(d_i), 
    .c_i(~c_i), 
    .q_o(qm)
  );

d_latch d_latch_slave(
    .d_i(qm),
    .c_i(c_i),
    .q_o(q_o),
    .qn_o(qn_o)
  );

endmodule

HomeTask_2/d_flip_flop_tb.v
`timescale 1ns/10ps

module d_flip_flop_tb();

reg DATA; // registers for input signals
reg COND; 
wire Q;   // wires for output signals
wire QN; 

d_flip_flop d_flip_flop_inst(
    .d_i(DATA), // data
    .c_i(COND), // condition
    .q_o(Q),
    .qn_o(QN)
);

realtime period = 10; // setting period variable

always #(period) COND = ~COND; // setting clk inverting every period 

initial 
begin
    $dumpvars;
    COND = 1'b0;
    DATA = 1'b0;
    #10 DATA = 1'b1;
    #20 DATA = 1'b0;

    #100 $finish;
end

initial
begin
    $monitor("simtime = %g, DATA =%b, COND =%b, Q =%b, QN =%b", $time,DATA,COND,Q, QN);
end

endmodule

HomeTask_2/dump.vcd
$date
	Sat Apr  2 02:43:39 2022
$end
$version
	Icarus Verilog
$end
$timescale
	10ps
$end
$scope module d_flip_flop_tb $end
$var wire 1 ! QN $end
$var wire 1 " Q $end
$var reg 1 # COND $end
$var reg 1 $ DATA $end
$var real 1 % period $end
$scope module d_flip_flop_inst $end
$var wire 1 # c_i $end
$var wire 1 $ d_i $end
$var wire 1 ! qn_o $end
$var wire 1 & qm $end
$var wire 1 " q_o $end
$scope module d_latch_master $end
$var wire 1 ' c_i $end
$var wire 1 $ d_i $end
$var wire 1 ( r $end
$var wire 1 ) s $end
$var wire 1 * qn_o $end
$var wire 1 & q_o $end
$scope module sr_latch_inst $end
$var wire 1 & q_o $end
$var wire 1 * qn_o $end
$var wire 1 ( r_i $end
$var wire 1 ) s_i $end
$upscope $end
$upscope $end
$scope module d_latch_slave $end
$var wire 1 # c_i $end
$var wire 1 & d_i $end
$var wire 1 + r $end
$var wire 1 , s $end
$var wire 1 ! qn_o $end
$var wire 1 " q_o $end
$scope module sr_latch_inst $end
$var wire 1 " q_o $end
$var wire 1 ! qn_o $end
$var wire 1 + r_i $end
$var wire 1 , s_i $end
$upscope $end
$upscope $end
$upscope $end
$upscope $end
$enddefinitions $end
#0
$dumpvars
1,
1+
0*
1)
0(
1'
1&
r10 %
0$
0#
0"
0!
$end
#1000
1"
0+
0&
0!
1(
1,
0'
1$
1#
#2000
1*
0"
0)
1+
1'
0#
#3000
1"
0*
0+
1)
0'
1#
0$
#4000
1&
0"
0(
1+
1'
0#
#5000
1"
0+
0&
0!
1(
1,
0'
1#
#6000
1&
0"
0(
1+
1'
0#
#7000
1"
0+
0&
0!
1(
1,
0'
1#
#8000
1&
0"
0(
1+
1'
0#
#9000
1"
0+
0&
0!
1(
1,
0'
1#
#10000
1&
0"
0(
1+
1'
0#
#11000
1"
0+
0&
0!
1(
1,
0'
1#
#12000
1&
0"
0(
1+
1'
0#
#13000
1"
0+
0&
0!
1(
1,
0'
1#
